{
  "post": {
    "id": 43028,
    "date": "2025-03-16T17:34:28",
    "date_gmt": "2025-03-16T17:34:28",
    "modified": "2025-03-16T17:34:28",
    "modified_gmt": "2025-03-16T17:34:28",
    "slug": "2025-website-marketing-best-practices-for-nonprofits",
    "link": "https://www.nptechforgood.com/2025/03/16/2025-website-marketing-best-practices-for-nonprofits/",
    "title": {
      "rendered": "2025 Website Marketing Best Practices for Nonprofits"
    },
    "content": {
      "rendered": "<p><a href=\"https://www.nptechforgood.com/101-best-practices/10-website-design-best-practices-for-nonprofits/\">Your website is the foundation upon which your digital marketing and fundraising campaigns are built</a>. How well your nonprofit&#8217;s email and social media campaigns perform depends upon how well your website communicates your mission and programs and whether it is optimized to capture leads and inspire action.</p>\n",
      "protected": false
    },
    "excerpt": {
      "rendered": "<p>Your website is the foundation upon which your digital marketing and fundraising campaigns are built. How well your nonprofit&#8217;s email and social media campaigns perform depends upon how well your website communicates your mission and programs and whether it is optimized to capture leads and inspire action.\u00a0</p>\n",
      "protected": false
    },
    "author": 1,
    "featured_media": 0,
    "categories": [
      93
    ],
    "tags": []
  },
  "image_refs": []
}