{
  "id": 41557,
  "date": "2024-10-09T16:51:14",
  "date_gmt": "2024-10-09T16:51:14",
  "guid": {
    "rendered": "https://www.nptechforgood.com/wp-content/uploads/2024/10/Plummer-Youth-Promise-Nonprofit.png"
  },
  "modified": "2024-10-09T16:51:14",
  "modified_gmt": "2024-10-09T16:51:14",
  "slug": "plummer-youth-promise-nonprofit",
  "status": "inherit",
  "type": "attachment",
  "link": "https://www.nptechforgood.com/2024/10/11/7-ways-to-grow-your-nonprofit-donor-base-with-social-media/plummer-youth-promise-nonprofit/",
  "title": {
    "rendered": "Plummer Youth Promise &#8211; Nonprofit"
  },
  "author": 1,
  "featured_media": 0,
  "comment_status": "",
  "ping_status": "closed",
  "template": "",
  "meta": {
    "_acf_changed": false,
    "advanced_seo_description": "",
    "jetpack_seo_html_title": "",
    "jetpack_seo_noindex": false,
    "jetpack_post_was_ever_published": false
  },
  "class_list": [
    "post-41557",
    "attachment",
    "type-attachment",
    "status-inherit",
    "hentry"
  ],
  "acf": [],
  "jetpack_shortlink": "https://wp.me/a3Gfd4-aOh",
  "jetpack_sharing_enabled": true,
  "description": {
    "rendered": "<p class=\"attachment\"><a href=\"https://i0.wp.com/www.nptechforgood.com/wp-content/uploads/2024/10/Plummer-Youth-Promise-Nonprofit-e1728634310310.png?ssl=1\"><img loading=\"lazy\" decoding=\"async\" width=\"150\" height=\"300\" src=\"https://i0.wp.com/www.nptechforgood.com/wp-content/uploads/2024/10/Plummer-Youth-Promise-Nonprofit-e1728634310310.png?fit=150%2C300&amp;ssl=1\" class=\"attachment-medium size-medium\" alt=\"\" /></a></p>\n"
  },
  "caption": {
    "rendered": ""
  },
  "alt_text": "",
  "media_type": "image",
  "mime_type": "image/png",
  "media_details": {
    "width": 400,
    "height": 800,
    "file": "2024/10/Plummer-Youth-Promise-Nonprofit-e1728634310310.png",
    "filesize": 150991,
    "sizes": {
      "medium": {
        "file": "Plummer-Youth-Promise-Nonprofit-150x300.png",
        "width": 150,
        "height": 300,
        "filesize": 36623,
        "mime_type": "image/png",
        "source_url": "https://i0.wp.com/www.nptechforgood.com/wp-content/uploads/2024/10/Plummer-Youth-Promise-Nonprofit-e1728634310310.png?fit=150%2C300&ssl=1"
      },
      "large": {
        "file": "Plummer-Youth-Promise-Nonprofit-512x1024.png",
        "width": 512,
        "height": 1024,
        "filesize": 264601,
        "mime_type": "image/png",
        "source_url": "https://i0.wp.com/www.nptechforgood.com/wp-content/uploads/2024/10/Plummer-Youth-Promise-Nonprofit-e1728634310310.png?fit=512%2C1024&ssl=1"
      },
      "thumbnail": {
        "file": "Plummer-Youth-Promise-Nonprofit-150x150.png",
        "width": 150,
        "height": 150,
        "filesize": 23083,
        "mime_type": "image/png",
        "source_url": "https://i0.wp.com/www.nptechforgood.com/wp-content/uploads/2024/10/Plummer-Youth-Promise-Nonprofit-e1728634310310.png?resize=150%2C150&ssl=1"
      },
      "medium_large": {
        "file": "Plummer-Youth-Promise-Nonprofit-768x1536.png",
        "width": 768,
        "height": 1536,
        "filesize": 490163,
        "mime_type": "image/png",
        "source_url": "https://i0.wp.com/www.nptechforgood.com/wp-content/uploads/2024/10/Plummer-Youth-Promise-Nonprofit-e1728634310310.png?fit=768%2C1536&ssl=1"
      },
      "1536x1536": {
        "file": "Plummer-Youth-Promise-Nonprofit-768x1536.png",
        "width": 768,
        "height": 1536,
        "filesize": 490163,
        "mime_type": "image/png",
        "source_url": "https://i0.wp.com/www.nptechforgood.com/wp-content/uploads/2024/10/Plummer-Youth-Promise-Nonprofit-e1728634310310.png?fit=768%2C1536&ssl=1"
      },
      "post-thumbnail": {
        "file": "Plummer-Youth-Promise-Nonprofit-200x200.png",
        "width": 200,
        "height": 200,
        "filesize": 38239,
        "mime_type": "image/png",
        "source_url": "https://i0.wp.com/www.nptechforgood.com/wp-content/uploads/2024/10/Plummer-Youth-Promise-Nonprofit-e1728634310310.png?resize=200%2C200&ssl=1"
      },
      "icon": {
        "file": "Plummer-Youth-Promise-Nonprofit-25x50.png",
        "width": 25,
        "height": 50,
        "filesize": 1743,
        "mime_type": "image/png",
        "source_url": "https://i0.wp.com/www.nptechforgood.com/wp-content/uploads/2024/10/Plummer-Youth-Promise-Nonprofit-e1728634310310.png?fit=25%2C50&ssl=1"
      },
      "featured": {
        "file": "Plummer-Youth-Promise-Nonprofit-200x200.png",
        "width": 200,
        "height": 200,
        "filesize": 38239,
        "mime_type": "image/png",
        "source_url": "https://i0.wp.com/www.nptechforgood.com/wp-content/uploads/2024/10/Plummer-Youth-Promise-Nonprofit-e1728634310310.png?resize=200%2C200&ssl=1"
      },
      "related": {
        "file": "Plummer-Youth-Promise-Nonprofit-75x75.png",
        "width": 75,
        "height": 75,
        "filesize": 6917,
        "mime_type": "image/png",
        "source_url": "https://i0.wp.com/www.nptechforgood.com/wp-content/uploads/2024/10/Plummer-Youth-Promise-Nonprofit-e1728634310310.png?resize=75%2C75&ssl=1"
      },
      "slider": {
        "file": "Plummer-Youth-Promise-Nonprofit-600x250.png",
        "width": 600,
        "height": 250,
        "filesize": 102768,
        "mime_type": "image/png",
        "source_url": "https://i0.wp.com/www.nptechforgood.com/wp-content/uploads/2024/10/Plummer-Youth-Promise-Nonprofit-e1728634310310.png?resize=400%2C250&ssl=1"
      },
      "splash-featured": {
        "file": "Plummer-Youth-Promise-Nonprofit-200x200.png",
        "width": 200,
        "height": 200,
        "filesize": 38239,
        "mime_type": "image/png",
        "source_url": "https://i0.wp.com/www.nptechforgood.com/wp-content/uploads/2024/10/Plummer-Youth-Promise-Nonprofit-e1728634310310.png?resize=200%2C200&ssl=1"
      },
      "splash-widgetthumb": {
        "file": "Plummer-Youth-Promise-Nonprofit-80x80.png",
        "width": 80,
        "height": 80,
        "filesize": 7541,
        "mime_type": "image/png",
        "source_url": "https://i0.wp.com/www.nptechforgood.com/wp-content/uploads/2024/10/Plummer-Youth-Promise-Nonprofit-e1728634310310.png?resize=80%2C80&ssl=1"
      },
      "splash-widgetfull": {
        "file": "Plummer-Youth-Promise-Nonprofit-324x200.png",
        "width": 324,
        "height": 200,
        "filesize": 62553,
        "mime_type": "image/png",
        "source_url": "https://i0.wp.com/www.nptechforgood.com/wp-content/uploads/2024/10/Plummer-Youth-Promise-Nonprofit-e1728634310310.png?resize=324%2C200&ssl=1"
      },
      "splash-related": {
        "file": "Plummer-Youth-Promise-Nonprofit-75x75.png",
        "width": 75,
        "height": 75,
        "filesize": 6917,
        "mime_type": "image/png",
        "source_url": "https://i0.wp.com/www.nptechforgood.com/wp-content/uploads/2024/10/Plummer-Youth-Promise-Nonprofit-e1728634310310.png?resize=75%2C75&ssl=1"
      },
      "splash-slider": {
        "file": "Plummer-Youth-Promise-Nonprofit-610x250.png",
        "width": 610,
        "height": 250,
        "filesize": 107361,
        "mime_type": "image/png",
        "source_url": "https://i0.wp.com/www.nptechforgood.com/wp-content/uploads/2024/10/Plummer-Youth-Promise-Nonprofit-e1728634310310.png?resize=400%2C250&ssl=1"
      },
      "wp_review_small": {
        "file": "Plummer-Youth-Promise-Nonprofit-80x80.png",
        "width": 80,
        "height": 80,
        "filesize": 7541,
        "mime_type": "image/png",
        "source_url": "https://i0.wp.com/www.nptechforgood.com/wp-content/uploads/2024/10/Plummer-Youth-Promise-Nonprofit-e1728634310310.png?resize=80%2C80&ssl=1"
      },
      "wp_review_large": {
        "file": "Plummer-Youth-Promise-Nonprofit-324x200.png",
        "width": 324,
        "height": 200,
        "filesize": 62553,
        "mime_type": "image/png",
        "source_url": "https://i0.wp.com/www.nptechforgood.com/wp-content/uploads/2024/10/Plummer-Youth-Promise-Nonprofit-e1728634310310.png?resize=324%2C200&ssl=1"
      },
      "full": {
        "file": "Plummer-Youth-Promise-Nonprofit-e1728634310310.png?fit=400%2C800&ssl=1",
        "width": 400,
        "height": 800,
        "mime_type": "image/png",
        "source_url": "https://i0.wp.com/www.nptechforgood.com/wp-content/uploads/2024/10/Plummer-Youth-Promise-Nonprofit-e1728634310310.png?fit=400%2C800&ssl=1"
      }
    },
    "image_meta": {
      "aperture": "0",
      "credit": "",
      "camera": "",
      "caption": "",
      "created_timestamp": "0",
      "copyright": "",
      "focal_length": "0",
      "iso": "0",
      "shutter_speed": "0",
      "title": "",
      "orientation": "0",
      "keywords": []
    }
  },
  "post": 41556,
  "source_url": "https://www.nptechforgood.com/wp-content/uploads/2024/10/Plummer-Youth-Promise-Nonprofit-e1728634310310.png",
  "_links": {
    "self": [
      {
        "href": "https://www.nptechforgood.com/wp-json/wp/v2/media/41557",
        "targetHints": {
          "allow": [
            "GET"
          ]
        }
      }
    ],
    "collection": [
      {
        "href": "https://www.nptechforgood.com/wp-json/wp/v2/media"
      }
    ],
    "about": [
      {
        "href": "https://www.nptechforgood.com/wp-json/wp/v2/types/attachment"
      }
    ],
    "author": [
      {
        "embeddable": true,
        "href": "https://www.nptechforgood.com/wp-json/wp/v2/users/1"
      }
    ],
    "replies": [
      {
        "embeddable": true,
        "href": "https://www.nptechforgood.com/wp-json/wp/v2/comments?post=41557"
      }
    ],
    "wp:attached-to": [
      {
        "embeddable": true,
        "post_type": "post",
        "id": 41556,
        "href": "https://www.nptechforgood.com/wp-json/wp/v2/posts/41556"
      }
    ],
    "curies": [
      {
        "name": "wp",
        "href": "https://api.w.org/{rel}",
        "templated": true
      }
    ]
  }
}