{
  "post_id": 11088,
  "post_url": "https://www.nptechforgood.com/2014/01/28/how-to-curate-nonprofit-videos-on-youtube/",
  "post_date": "2014-01-28T13:30:45",
  "post_title": "HOW TO: Curate Nonprofit Videos on YouTube",
  "images": [
    {
      "position": 0,
      "media_id": 15459,
      "src_display": "https://i0.wp.com/www.nptechforgood.com/wp-content/uploads/2014/01/YouTube-Playlists-Nonprofits-300x300.jpg?resize=300%2C300",
      "src_original": "https://i0.wp.com/www.nptechforgood.com/wp-content/uploads/2014/01/YouTube-Playlists-Nonprofits-300x300.jpg",
      "local_file": "11088-01.jpg",
      "alt": "YouTube Playlists Nonprofits",
      "alt_source": "inline",
      "section_heading": null,
      "width": 500,
      "height": 500
    },
    {
      "position": 1,
      "media_id": 15449,
      "src_display": "https://i0.wp.com/www.nptechforgood.com/wp-content/uploads/2014/01/YouTube-Nonprofits-One.png?resize=600%2C442",
      "src_original": "https://i0.wp.com/www.nptechforgood.com/wp-content/uploads/2014/01/YouTube-Nonprofits-One.png",
      "local_file": "11088-02.png",
      "alt": "YouTube Nonprofits One",
      "alt_source": "inline",
      "section_heading": "Step 1: Create a playlist of at least four videos.",
      "width": 600,
      "height": 442
    },
    {
      "position": 2,
      "media_id": 15450,
      "src_display": "https://i0.wp.com/www.nptechforgood.com/wp-content/uploads/2014/01/YouTube-Nonprofits-Two.png?resize=600%2C493",
      "src_original": "https://i0.wp.com/www.nptechforgood.com/wp-content/uploads/2014/01/YouTube-Nonprofits-Two.png",
      "local_file": "11088-03.png",
      "alt": "YouTube Nonprofits Two",
      "alt_source": "inline",
      "section_heading": "Step 1: Create a playlist of at least four videos.",
      "width": 600,
      "height": 493
    },
    {
      "position": 3,
      "media_id": 15452,
      "src_display": "https://i0.wp.com/www.nptechforgood.com/wp-content/uploads/2014/01/YouTube-Nonprofits-Three.png?resize=600%2C245",
      "src_original": "https://i0.wp.com/www.nptechforgood.com/wp-content/uploads/2014/01/YouTube-Nonprofits-Three.png",
      "local_file": "11088-04.png",
      "alt": "YouTube Nonprofits Three",
      "alt_source": "inline",
      "section_heading": "Step 2: Add your new playlist as a section to your channel.",
      "width": 600,
      "height": 245
    },
    {
      "position": 4,
      "media_id": 15453,
      "src_display": "https://i0.wp.com/www.nptechforgood.com/wp-content/uploads/2014/01/YouTube-Nonprofits-Four.png?resize=600%2C304",
      "src_original": "https://i0.wp.com/www.nptechforgood.com/wp-content/uploads/2014/01/YouTube-Nonprofits-Four.png",
      "local_file": "11088-05.png",
      "alt": "YouTube Nonprofits Four",
      "alt_source": "inline",
      "section_heading": "Step 2: Add your new playlist as a section to your channel.",
      "width": 600,
      "height": 304
    },
    {
      "position": 5,
      "media_id": 15454,
      "src_display": "https://i0.wp.com/www.nptechforgood.com/wp-content/uploads/2014/01/YouTube-Nonprofits-Five.png?resize=600%2C159",
      "src_original": "https://i0.wp.com/www.nptechforgood.com/wp-content/uploads/2014/01/YouTube-Nonprofits-Five.png",
      "local_file": "11088-06.png",
      "alt": "YouTube Nonprofits Five",
      "alt_source": "inline",
      "section_heading": "Step 2: Add your new playlist as a section to your channel.",
      "width": 600,
      "height": 159
    },
    {
      "position": 6,
      "media_id": 15455,
      "src_display": "https://i0.wp.com/www.nptechforgood.com/wp-content/uploads/2014/01/YouTube-Nonprofits-Seven.png?resize=600%2C346",
      "src_original": "https://i0.wp.com/www.nptechforgood.com/wp-content/uploads/2014/01/YouTube-Nonprofits-Seven.png",
      "local_file": "11088-07.png",
      "alt": "YouTube Nonprofits Seven",
      "alt_source": "inline",
      "section_heading": "youtube.com/nonprofitorgs",
      "width": 600,
      "height": 346
    }
  ]
}