{
  "post_id": 21197,
  "post_url": "https://www.nptechforgood.com/2017/05/08/how-to-create-a-peer-to-peer-fundraising-campaign-on-facebook-2/",
  "post_date": "2017-05-08T16:35:28",
  "post_title": "How to Create a Peer-to-Peer Fundraising Campaign on Facebook",
  "images": [
    {
      "position": 0,
      "media_id": 21204,
      "src_display": "https://i0.wp.com/www.nptechforgood.com/wp-content/uploads/2017/05/Facebook-Fundraisers-2.jpg?resize=600%2C448",
      "src_original": "https://i0.wp.com/www.nptechforgood.com/wp-content/uploads/2017/05/Facebook-Fundraisers-2.jpg",
      "local_file": "21197-01.jpg",
      "alt": "",
      "alt_source": "none",
      "section_heading": null,
      "width": 600,
      "height": 448
    },
    {
      "position": 1,
      "media_id": 21201,
      "src_display": "https://i0.wp.com/www.nptechforgood.com/wp-content/uploads/2017/05/Facebook-Fundraisers-1.jpg?resize=600%2C495",
      "src_original": "https://i0.wp.com/www.nptechforgood.com/wp-content/uploads/2017/05/Facebook-Fundraisers-1.jpg",
      "local_file": "21197-02.jpg",
      "alt": "",
      "alt_source": "none",
      "section_heading": null,
      "width": 600,
      "height": 495
    },
    {
      "position": 2,
      "media_id": 21205,
      "src_display": "https://i0.wp.com/www.nptechforgood.com/wp-content/uploads/2017/05/Facebook-Fundraisers-3.jpg?resize=600%2C548",
      "src_original": "https://i0.wp.com/www.nptechforgood.com/wp-content/uploads/2017/05/Facebook-Fundraisers-3.jpg",
      "local_file": "21197-03.jpg",
      "alt": "",
      "alt_source": "none",
      "section_heading": null,
      "width": 600,
      "height": 548
    },
    {
      "position": 3,
      "media_id": 21207,
      "src_display": "https://i0.wp.com/www.nptechforgood.com/wp-content/uploads/2017/05/Facebook-Fundraisers-4.png?resize=600%2C455",
      "src_original": "https://i0.wp.com/www.nptechforgood.com/wp-content/uploads/2017/05/Facebook-Fundraisers-4.png",
      "local_file": "21197-04.png",
      "alt": "",
      "alt_source": "none",
      "section_heading": null,
      "width": 600,
      "height": 455
    },
    {
      "position": 4,
      "media_id": 21215,
      "src_display": "https://i0.wp.com/www.nptechforgood.com/wp-content/uploads/2017/05/thank-you-emails.jpg?resize=600%2C310",
      "src_original": "https://i0.wp.com/www.nptechforgood.com/wp-content/uploads/2017/05/thank-you-emails.jpg",
      "local_file": "21197-05.jpg",
      "alt": "",
      "alt_source": "none",
      "section_heading": null,
      "width": 600,
      "height": 310
    },
    {
      "position": 5,
      "media_id": 21183,
      "src_display": "https://i0.wp.com/www.nptechforgood.com/wp-content/uploads/2017/05/English-Survey-Promo-600x200.png?resize=600%2C200",
      "src_original": "https://i0.wp.com/www.nptechforgood.com/wp-content/uploads/2017/05/English-Survey-Promo-600x200.png",
      "local_file": "21197-06.png",
      "alt": "",
      "alt_source": "none",
      "section_heading": "Which emotion motivates you most often to donate to nonprofits? Anger? Empathy? Fear? Hope?Take the survey!givingreport.ngo",
      "width": 600,
      "height": 200
    }
  ]
}