{
  "post_id": 24941,
  "post_url": "https://www.nptechforgood.com/2019/12/15/free-webinar-how-to-create-an-engaging-donor-journey-in-2020/",
  "post_date": "2019-12-15T14:49:59",
  "post_title": "[FREE WEBINAR] How to Create an Engaging Donor Journey in 2020",
  "images": [
    {
      "position": 0,
      "media_id": 24950,
      "src_display": "https://i0.wp.com/www.nptechforgood.com/wp-content/uploads/2019/12/Engaging-Donor-Journey-Nonprofits.png?resize=960%2C480",
      "src_original": "https://i0.wp.com/www.nptechforgood.com/wp-content/uploads/2019/12/Engaging-Donor-Journey-Nonprofits.png",
      "local_file": "24941-01.png",
      "alt": "",
      "alt_source": "none",
      "section_heading": null,
      "width": 1024,
      "height": 512
    }
  ]
}